splitcli/__init__.py
splitcli/__main__.py
splitcli/accounts/__init__.py
splitcli/accounts/signin.py
splitcli/accounts/signup.py
splitcli/accounts/user.py
splitcli/config/__init__.py
splitcli/experiment/__init__.py
splitcli/experiment/batch_client.py
splitcli/experiment/event_result.py
splitcli/experiment/experiment.py
splitcli/experiment/weights.py
splitcli/split_apis/__init__.py
splitcli/split_apis/definitions_api.py
splitcli/split_apis/environments_api.py
splitcli/split_apis/http_client.py
splitcli/split_apis/segments_api.py
splitcli/split_apis/splits_api.py
splitcli/split_apis/traffic_types_api.py
splitcli/split_apis/users_api.py
splitcli/split_apis/workspaces_api.py
splitcli/splitio_selectors/__init__.py
splitcli/splitio_selectors/core_selectors.py
splitcli/splitio_selectors/definition_selectors.py
splitcli/splitio_selectors/metric_selectors.py
splitcli/splitio_selectors/organization_selectors.py
splitcli/splitio_selectors/segment_selectors.py
splitcli/splitio_selectors/split_selectors.py
splitcli/templates/__init__.py
splitcli/templates/split_templates.py
splitcli/ux/__init__.py
splitcli/ux/hex_color.py
splitcli/ux/menu.py
splitcli/ux/text.py
splitcli-0.2.0.dist-info/LICENSE.txt
splitcli-0.2.0.dist-info/METADATA
splitcli-0.2.0.dist-info/WHEEL
splitcli-0.2.0.dist-info/entry_points.txt
splitcli-0.2.0.dist-info/top_level.txt
splitcli-0.2.0.dist-info/RECORD
