Metadata-Version: 2.1
Name: splitcli
Version: 0.2.0
Summary: Use Split.io from the command line
Home-page: https://github.com/splitio-examples/splitcli
Author: Henry Jewkes &  Talia Nassi & Micah Silverman
Author-email: info@split.io
License: UNKNOWN
Project-URL: Bug Reports, https://github.com/splitio-examples/splitcli/issues
Project-URL: Source, https://github.com/splitio-examples/splitcli
Keywords: development,split,feature flags
Platform: UNKNOWN
Classifier: Development Status :: 3 - Alpha
Classifier: Intended Audience :: Developers
Classifier: Topic :: Software Development
Classifier: License :: OSI Approved :: Apache Software License
Classifier: Programming Language :: Python :: 3.6
Classifier: Programming Language :: Python :: 3.7
Classifier: Programming Language :: Python :: 3.8
Classifier: Programming Language :: Python :: 3.9
Classifier: Programming Language :: Python :: 3 :: Only
Requires-Python: >=3.6, <4
License-File: LICENSE.txt
Requires-Dist: requests
Requires-Dist: python-inquirer
Requires-Dist: art
Requires-Dist: inquirer
Provides-Extra: dev
Requires-Dist: check-manifest ; extra == 'dev'
Provides-Extra: test
Requires-Dist: coverage ; extra == 'test'
